{
    "topics": {
        "Unidad 1: Materia y Energía": {
            "questions": [
                {
                    "question": "Corresponde a un proceso físico que libera la mayor cantidad de calor:",
                    "year": "2016 1P",
                    "imageURL": "",
                    "options": [
                        "Solidificación",
                        "Ebullición",
                        "Combustión",
                        "Deposición",
                        "Fusión"
                    ],
                    "answer": "d",
                    "explicacion": "Solidificación (A): Libera calor (exotérmico) al pasar de líquido a sólido, pero no libera tanta energía como la Deposición. <br>Ebullición (B): Es endotérmico (absorbe calor al pasar de líquido a gas). <br>Combustión (C): Aunque libera mucho calor, es un proceso químico (no físico). <br>Deposición (D): Gas → sólido, libera más calor que el de solidificación (ejemplo: vapor de agua → hielo). <br>Fusión (E): Endotérmico (absorbe calor al pasar de sólido a líquido). <br>La deposición, al implicar un cambio de fase con mayor energía (sublimación inversa), libera más calor que la solidificación.",
                    "imageURLans": ""
                },
                {
                    "question": "Corresponde a un proceso físico y químico que liberan calor:",
                    "year": "2016 1P",
                    "imageURL": "",
                    "options": [
                        "Sublimación y electrólisis de cloruro de sodio.",
                        "Condensación y combustión de etanol.",
                        "Combustión y descomposición de clorato de potasio.",
                        "Deposición y solidificación de agua gaseosa.",
                        "Fusión y sublimación del yodo sólido."
                    ],
                    "answer": "b"
                },
                {
                    "question": "El dióxido de carbono es una sustancia compuesta porque:",
                    "year": "2016 1P",
                    "imageURL": "",
                    "options": [
                        "Presenta 3 átomos de elementos iguales.",
                        "Da 2 elementos diferentes por descomposición.",
                        "Es capaz de oxidarse frente al oxígeno.",
                        "Da 2 elementos diferentes por reacción de composición.",
                        "Porque presenta mayor densidad que el oxígeno."
                    ],
                    "answer": "b"
                },
                {
                    "question": "El proceso que requiere energía es:",
                    "year": "2016",
                    "imageURL": "",
                    "options": [
                        "",
                        "1 N",
                        "2 N",
                        "4 N",
                        "8 N"
                    ],
                    "answer": "d"
                }
            ]
        },
        "Unidad 2: Cinemática": {
            "subtopics": {
                "Cinemática Conceptual y Movimiento Uniforme": {
                    "questions": []
                },
                "Movimiento Uniformemente Variado": {
                    "questions": []
                },
                "Tiro Vertical y Caída Libre": {
                    "questions": []
                },
                "Movimiento Parabólico": {
                    "questions": []
                },
                "Movimiento Circular Uniforme": {
                    "questions": []
                },
                "Composición de Movimientos": {
                    "questions": []
                }
            }
        },
        "Unidad 3: Dinámica": {
            "subtopics": {
                "Dinámica de los Cuerpos": {
                    "questions": []
                },
                "Trabajo, Energía y Potencia": {
                    "questions": []
                }
            }
        },
        "Unidad 7: Disoluciones y sus propiedades": {
            "questions": [
                {
                    "question": "El iodo y el cloruro de sodio son solubles respectivamente en:",
                    "year": "",
                    "imageURL": "",
                    "options": [
                        "Benceno (C<sub>6</sub>H<sub>6</sub>) y octano (C<sub>8</sub>H<sub>18</sub>)",
                        "Agua y amoniaco",
                        "Hexano (C<sub>6</sub>H<sub>6</sub>) y benceno (C<sub>6</sub>H<sub>6</sub>)",
                        "Hexano (C<sub>6</sub>H<sub>6</sub>) y agua",
                        "Agua y etanol (C<sub>2</sub>H<sub>5</sub>OH)"
                    ],
                    "answer": "d",
                    "explicacion": "El iodo es soluble en solventes no polares como el hexano (C<sub>6</sub>H<sub>6</sub>), mientras que el cloruro de sodio es soluble en agua (polar). La opción D combina correctamente estos pares.",
                    "imageURLans": ""
                },
                {
                    "question": "Una solución sobresaturada se obtiene cuando:",
                    "year": "",
                    "imageURL": "",
                    "options": [
                        "La concentración de soluto disuelto es mayor a la constante de solubilidad.",
                        "La concentración de soluto disuelto es igual a la constante de solubilidad.",
                        "La concentración de soluto disuelto es menor a la constante de solubilidad.",
                        "La concentración de soluto no disuelto es mayor a la constante de solubilidad.",
                        "La concentración de soluto no disuelto es menor a la constante de solubilidad."
                    ],
                    "answer": "a",
                    "explicacion": "Una solución sobresaturada contiene más soluto disuelto (A) que el permitido por su solubilidad en condiciones de equilibrio. Esto se logra alterando condiciones como temperatura y luego enfriando lentamente.",
                    "imageURLans": ""
                },
                {
                    "question": "Se tiene una solución sobresaturada, al mismo se le adiciona más solvente, podemos afirmar que:",
                    "year": "",
                    "imageURL": "",
                    "options": [
                        "La cantidad de soluto disminuirá en la solución.",
                        "La relación soluto/solvente permanece constante.",
                        "La concentración molar de la solución disminuye.",
                        "La concentración porcentual aumenta.",
                        "El punto de ebullición de la solución no varía."
                    ],
                    "answer": "c",
                    "explicacion": "Al añadir solvente (C), la concentración molar disminuye porque el volumen total aumenta mientras los moles de soluto se mantienen constantes. La solución dejará de estar sobresaturada.",
                    "imageURLans": ""
                },
                {
                    "question": "Una solución exotérmica, es cuando mezclan:",
                    "year": "",
                    "imageURL": "",
                    "options": [
                        "soluto-solvente y absorbe calor.",
                        "soluto-soluto y libera calor.",
                        "soluto-soluto y absorbe calor.",
                        "soluto-solvente y libera calor.",
                        "solvente-solvente y libera calor."
                    ],
                    "answer": "d",
                    "explicacion": "Una solución exotérmica (D) libera calor durante el proceso de solvatación, donde las moléculas de solvente rodean al soluto (interacción soluto-solvente).",
                    "imageURLans": ""
                },
                {
                    "question": "La que NO representa una característica de un proceso de dilución:",
                    "year": "",
                    "imageURL": "",
                    "options": [
                        "Al diluir se obtiene una solución menos concentrada.",
                        "Se produce al agregar más disolvente a la solución inicial.",
                        "El número de moles del soluto permanece constante.",
                        "Cambia el número total de partículas de soluto.",
                        "El volumen de la solución."
                    ],
                    "answer": "d",
                    "explicacion": "En una dilución (D), el número de partículas de soluto no cambia (solo se dispersan en más solvente). Las otras opciones son verdaderas: la concentración disminuye, se añade solvente y el volumen aumenta.",
                    "imageURLans": ""
                },
                {
                    "question": "Es un ejemplo de coloide tipo Gel:",
                    "year": "",
                    "imageURL": "",
                    "options": [
                        "mayonesa.",
                        "niebla.",
                        "humo.",
                        "mantequilla.",
                        "espuma."
                    ],
                    "answer": "a",
                    "explicacion": "Un gel (A) es un coloide donde partículas sólidas forman una red en un líquido. La mayonesa es un ejemplo (gotas de aceite en agua estabilizadas por lecitina).",
                    "imageURLans": ""
                },
                {
                    "question": "Los gramos de cloruro de sodio que son necesarios para preparar 240 mL de solución al 0,47M, es: (PA: Na= 23, Cl= 35,5)",
                    "year": "",
                    "imageURL": "",
                    "options": [
                        "3,52 g",
                        "4,53 g",
                        "6,60 g",
                        "2,83 g",
                        "1,41 g"
                    ],
                    "answer": "c",
                    "explicacion": "Moles = M × V = 0.47 × 0.24 = 0.1128 mol. Masa = moles × PM (58.5 g/mol) = 6.60 g (C).",
                    "imageURLans": ""
                },
                {
                    "question": "Los gramos de hidróxido de sodio que se requieren para 150 ml de una solución de hidróxido de sodio al 4,3 % (p/v), es:",
                    "year": "",
                    "imageURL": "",
                    "options": [
                        "2,45 g",
                        "3,45 g",
                        "4,45 g",
                        "6,45 g",
                        "7,45 g"
                    ],
                    "answer": "d",
                    "explicacion": "%p/v = (masa soluto/volumen solución)×100. Masa = (4.3 × 150)/100 = 6.45 g (D).",
                    "imageURLans": ""
                },
                {
                    "question": "La masa en gramos de ácido sulfúrico que hay en 200 gramos de solvente en una solución 0,3 molal, es: (PA: H= 1, S= 32, O= 16)",
                    "year": "",
                    "imageURL": "",
                    "options": [
                        "588",
                        "5,88",
                        "666,6",
                        "6,66",
                        "2,88"
                    ],
                    "answer": "b",
                    "explicacion": "Molalidad = moles soluto/kg solvente. Moles = 0.3 × 0.2 = 0.06 mol. Masa = moles × PM (98 g/mol) = 5.88 g (B).",
                    "imageURLans": ""
                },
                {
                    "question": "La concentración de una solución que se prepara a partir de 2,5 gramos de permanganato de potasio que se disuelven hasta completar un volumen de solución de 250 ml es: (PA: K= 39, Mn= 55, O= 16)",
                    "year": "",
                    "imageURL": "",
                    "options": [
                        "0,31 M",
                        "2,5 %(p/v)",
                        "6,3x10<sup>2</sup> N",
                        "1,26x10<sup>-2</sup> N",
                        "6,3x10<sup>-2</sup> M"
                    ],
                    "answer": "e",
                    "explicacion": "Moles = 2.5 g / 158 g/mol = 0.0158 mol. Molaridad = 0.0158/0.25 L = 0.063 M (E). %p/v = (2.5/250)×100 = 1% (no es opción).",
                    "imageURLans": ""
                },
                {
                    "question": "La normalidad de una solución que se prepara disolviendo 6,6 g de carbonato de potasio hasta obtener 150 mL de solución es: (PA: K= 39, C= 12, O= 16)",
                    "year": "",
                    "imageURL": "",
                    "options": [
                        "0,6377 N",
                        "1,5645 N",
                        "0,0923 N",
                        "0,1333 N",
                        "0,3188 N"
                    ],
                    "answer": "a",
                    "explicacion": "Moles = 6.6 g / 138 g/mol = 0.0478 mol. Equivalente = 2 (por CO<sub>3</sub><sup>2-</sup>). Normalidad = (0.0478 × 2)/0.15 L = 0.6377 N (A).",
                    "imageURLans": ""
                },
                {
                    "question": "La normalidad de cloruro de aluminio que contiene 1,15 % (p/v) de aluminio, es:",
                    "year": "",
                    "imageURL": "",
                    "options": [
                        "3,8333 N",
                        "0,0426 N",
                        "1,2778 N",
                        "0,0861 N",
                        "0,1278 N"
                    ],
                    "answer": "c",
                    "explicacion": "1.15 g Al en 100 mL solución = 0.0426 mol Al. Equivalente = 3 (Al<sup>3+</sup>). Normalidad = (0.0426 × 3)/0.1 L = 1.2778 N (C).",
                    "imageURLans": ""
                },
                {
                    "question": "Se ha preparado una solución disolviendo 40,7 g de sulfato de hierro (III) en 120 ml de solución. La concentración de los iones Fe<sup>+3</sup> expresada en g/dL. es: (PA: Fe= 56, S= 32, O= 16)",
                    "year": "",
                    "imageURL": "",
                    "options": [
                        "24,4",
                        "14,2",
                        "9,50",
                        "8,16",
                        "4,76"
                    ],
                    "answer": "b",
                    "explicacion": "Moles Fe<sub>2</sub>(SO<sub>4</sub>)<sub>3</sub> = 40.7 g / 400 g/mol = 0.10175 mol. Moles Fe<sup>3+</sup> = 0.2035 mol. Masa Fe<sup>3+</sup> = 0.2035 × 56 = 11.4 g en 120 mL = 9.5 g/dL (C).",
                    "imageURLans": ""
                },
                {
                    "question": "Tomamos 175 mL de HCl concentrado de d= 1,14 g/mL y 37 % (p/p), se desea obtener un ácido clorhídrico diluido d= 1,08 g/mL con 18 % (p/p), el volumen de agua que se debe adicionar para preparar dicha solución es: (H= 1, CI= 35,5)",
                    "year": "",
                    "imageURL": "",
                    "options": [
                        "379,71 ml",
                        "204,71 ml",
                        "350,00 ml",
                        "30,56 ml",
                        "254,71 ml"
                    ],
                    "answer": "d",
                    "explicacion": "Masa HCl conc. = 175 mL × 1.14 g/mL = 199.5 g. Masa HCl puro = 199.5 × 0.37 = 73.815 g. Masa sol. diluida = 73.815 g / 0.18 = 410.08 g. Masa agua añadida = 410.08 - 199.5 = 210.58 g ≈ 210.58 mL (D).",
                    "imageURLans": ""
                },
                {
                    "question": "Se mezclan 400 mL de solución de cloruro de potasio al 0,567 N con 350 mL de sulfato de potasio al 3,5 % (p/v), los miliequivalentes de potasio presentes, son: (PA: K= 39, S= 32, O= 16, CI= 35,5)",
                    "year": "",
                    "imageURL": "",
                    "options": [
                        "508,4 mEq",
                        "735,2 mEq",
                        "297,2 mEq",
                        "367,6 mEq",
                        "594,4 mEq"
                    ],
                    "answer": "a",
                    "explicacion": "mEq KCl = 0.567 N × 400 mL = 226.8 mEq. mEq K<sub>2</sub>SO<sub>4</sub> = (3.5 g/100 mL × 350 mL × 2 eq/mol)/174 g/mol × 1000 = 281.6 mEq. Total = 508.4 mEq (A).",
                    "imageURLans": ""
                }
            ]
        }
    }
}
